{
	"entries": [
		{
				"message": "Running SetArtemisValues.script",
				"identifier": "START",
				"timestamp": "2023-11-20 15:42:52.654 -0500"
			},
		{
				"message": "(Duration:\"4.557\", Errors:\"1\", Exceptions:\"0\", StartTime:\"2023-11-20 15:42:52 -0500\", Successes:\"0\", TestCase:\"SetArtemisValues.script\", Warnings:\"0\")",
				"identifier": "EndTestCase",
				"timestamp": "2023-11-20 15:42:57.224 -0500"
			},
		{
				"image": "Screen_Error.png",
				"message": "SCPI ERROR: -100,\"Command error; CONF:RAD:BLE:TEMP:VAL <value> failed. Failed to set temperature value\" -- Execution Time 0:00:04 SetArtemisValues.script",
				"identifier": "FAILURE",
				"timestamp": "2023-11-20 15:42:57.681 -0500"
			}
	],
	"createdTimestamp": "2023-11-20 15:42:52.661 -0500"
}