{
	"entries": [
		{
				"message": "Running SetArtemisValues.script",
				"identifier": "START",
				"timestamp": "2023-11-15 16:41:58.109 -0500"
			},
		{
				"handlerName": "on_validatevaluesinthermometerapp",
				"timestamp": "2023-11-15 16:42:02.520 -0500",
				"scriptName": "ValidateValuesInThermometerApp.script",
				"message": "found at (952, 358)",
				"image": "HAACP_BatteryIcon_hollow",
				"handlerLine": 3,
				"identifier": "waitfor"
			},
		{
				"handlerName": "on_validatevaluesinthermometerapp",
				"timestamp": "2023-11-15 16:42:02.834 -0500",
				"message": "(311,506,861,774)",
				"scriptName": "ValidateValuesInThermometerApp.script",
				"handlerLine": 4,
				"identifier": "readtext"
			},
		{
				"message": "(Duration:\"56.346\", Errors:\"1\", Exceptions:\"0\", StartTime:\"2023-11-15 16:41:58 -0500\", Successes:\"0\", TestCase:\"SetArtemisValues.script\", Warnings:\"0\")",
				"identifier": "EndTestCase",
				"timestamp": "2023-11-15 16:42:54.476 -0500"
			},
		{
				"message": "Execution Time 0:00:56 SetArtemisValues.script",
				"identifier": "ABORTED",
				"timestamp": "2023-11-15 16:42:54.501 -0500"
			}
	],
	"createdTimestamp": "2023-11-15 16:41:58.123 -0500"
}